sw_ut_report/__init__.py
sw_ut_report/__main__.py
sw_ut_report/config.py
sw_ut_report/constants.py
sw_ut_report/jama_common.py
sw_ut_report/jama_ut_manager.py
sw_ut_report/parse_txt_file.py
sw_ut_report/parse_xml_file.py
sw_ut_report/push_ut_test_results.py
sw_ut_report/run.py
sw_ut_report/template_manager.py
sw_ut_report/test_status.py
sw_ut_report/unit_test_case_data.py
sw_ut_report/utils.py
sw_ut_report/path/to/venv/pyvenv.cfg
sw_ut_report/templates/combined_test_report.j2
sw_ut_report/templates/combined_test_report_html.j2
lupin_sw_ut_report-1.0.9.dist-info/LICENSE
lupin_sw_ut_report-1.0.9.dist-info/METADATA
lupin_sw_ut_report-1.0.9.dist-info/WHEEL
lupin_sw_ut_report-1.0.9.dist-info/entry_points.txt
lupin_sw_ut_report-1.0.9.dist-info/top_level.txt
lupin_sw_ut_report-1.0.9.dist-info/RECORD
