Metadata-Version: 2.1
Name: lupin-sw-ut-report
Version: 1.0.9
Summary: Tool used to generate a test reports.
Author-email: LupinDental <cedric.fdl-ext@lupindental.com>
Maintainer-email: LupinDental <cedric.fdl-ext@lupindental.com>
License: Copyright (c) 2024 LupinDental
Project-URL: Repository, https://gitlab.com/todo.add.url
Classifier: Programming Language :: Python :: 3.10
Classifier: Programming Language :: Python :: 3.11
Classifier: Programming Language :: Python :: 3.12
Classifier: Development Status :: 3 - Alpha
Requires-Python: >=3.10
License-File: LICENSE
Requires-Dist: jinja2==3.1.4
Requires-Dist: typer==0.12.3
Requires-Dist: devenv>=0.1.1
Requires-Dist: click==8.2.1
Provides-Extra: dev
Requires-Dist: coverage; extra == "dev"
Requires-Dist: pytest; extra == "dev"
Requires-Dist: pytest-cov; extra == "dev"
